{
  "slug": "assent",
  "name": "Assent Inc.",
  "shortName": "Assent",
  "displayName": "Assent Inc.",
  "website": "https://www.assent.com",
  "linkedin": "https://www.linkedin.com/company/assent",
  "forbesRank": null,
  "fortuneRank": null,
  "badges": [],
  "h1": "Assent's GCC footprint in India",
  "lede": "<strong>Assent runs one center in Pune.</strong> Pune, covering IT.",
  "insight": "A single Assent center is easy to miss and easier to misread. We track its type, functions and the people who run it, so you can decide if it belongs on your target list.",
  "metaTitle": "Assent Inc. GCC in India: Centers, Footprint & Leaders | Bamboo Reports",
  "metaDescription": "Assent runs 1 verified center in Pune, covering IT. See the full India footprint, org map and contacts on Bamboo Reports.",
  "stats": {
    "activeCenters": 1,
    "totalCenters": 1,
    "cities": [
      "Pune"
    ],
    "yearsInIndia": 1,
    "sinceYear": 2025,
    "headcountBand": "101 to 200",
    "headcountBandLong": "101 to 200"
  },
  "centerTypes": [
    "IT"
  ],
  "functions": [
    "IT",
    "Customer Support"
  ],
  "tech": {
    "tools": 2,
    "categories": 2,
    "categoryList": [
      "Cloud Platform",
      "Infrastructure as Code"
    ]
  },
  "leaders": {
    "count": 1,
    "departments": "GCC leadership",
    "titles": [
      {
        "title": "Managing Director, India Center Head and VP of Engineering",
        "city": "Pune"
      }
    ]
  },
  "about": {
    "description": "Assent's India footprint covers Pune, spanning IT. The centers deliver IT and Customer Support for the group's global operations.",
    "industry": "Pharma & Life Sciences",
    "headquarters": "Canada",
    "revenueBand": "$101Mn to $250Mn",
    "employeesBand": "501 to 1,000",
    "tickerAndType": "Private"
  },
  "bandCopy": "Exact center locations, per-center headcount, the technology stack and all one decision-makers, in one profile.",
  "faq": [
    {
      "q": "How many centers does Assent operate in India?",
      "a": "Assent operates 1 active center in India."
    },
    {
      "q": "Which Indian cities does Assent have centers in?",
      "a": "Assent's India presence is in Pune."
    },
    {
      "q": "What types of centers does Assent run in India?",
      "a": "Assent runs IT centers in India."
    },
    {
      "q": "How many people work at Assent's India centers?",
      "a": "Aggregate and center-level headcount for Assent's India operations is available in the full profile.",
      "excludeFromSchema": true
    },
    {
      "q": "Who leads Assent's GCC in India?",
      "a": "Bamboo Reports tracks leaders at Assent's India centers, across GCC leadership. Names and contact details open with a free account.",
      "excludeFromSchema": true
    }
  ],
  "dateModified": "2026-07-04",
  "lastUpdated": "July 2026",
  "sources": "company filings, LinkedIn, NASSCOM and Bamboo Reports' primary research",
  "confidence": "high",
  "related": [
    {
      "label": "GCCs in India",
      "href": "/gcc/"
    },
    {
      "label": "Explore India GCCs",
      "href": "/gcc"
    }
  ],
  "sponsor": null
}
